Workbook

Sheet README
A1: Tea Shop Ledger - converted from handwritten page
A3: Settings (edit the yellow cells; every sheet picks them up)
A4: Ledger date | C4: 45949 | D4: Handwritten date reads like 19/10/25 - please confirm
A5: Branch ID | C5: BR001 | D5: Branch not written on the page - placeholder, set the real branch ID (configurable per SRS section 3)
A8: Sheets (follow the SRS table design)
A9: Ledger_Raw - every line exactly as read from the photo (Col A / Col B / Col C = the three number columns). Orange rows need your review.
A10: Expenses - purchase lines mapped to SRS expense fields (category, sub-category, amount, payment mode, approval status).
A11: Staff_Payments - the name list on the right of the page, mapped to SRS employee advance / salary fields.
A12: Daily_Closing - SRS section 5/6 cash reconciliation and closing summary. Sales and actual cash were not on the page: fill the yellow cells.
A13: Category_Summary - expense totals by category (SRS section 7), with a check against the ledger.
A15: Assumptions made while reading the page
A16: 1. Column header on the page reads 'Collns'; its meaning for the three columns is unclear. Col B is treated as the final amount (it has the most entries). Col A and Col C are kept for reference.
A17: 2. 'Mill' written for Silk / Dh. / J. / Jaila / Pol. was read as Milk.
A18: 3. 'R.F' (2000 / 2000) is treated as opening cash / float, not a purchase.
A19: 4. All purchase lines are assumed paid in Cash (blue text) - change the payment mode where that is wrong.
A20: 5. Items I could not identify (G.J, C-gold, JOP, P.M.V, C-Yoll) are categorised 'Needs review'.
... A22: 7. Blue font = typed input / assumption, black = formula.

Sheet Ledger_Raw
A1: Line | B1: Date | C1: Item (as written) | D1: Item (interpreted) | E1: Col A | F1: Col B | G1: Col C | H1: Confidence | I1: Notes
A2: 1 | B2: =README!$C$4 -> 45949 | C2: R.F | D2: Opening cash / float | E2: 2000 | F2: 2000 | H2: Medium | I2: Not a purchase; used as opening cash
A3: 2 | B3: =README!$C$4 -> 45949 | C3: Silk Mill | D3: Silk Milk | E3: 1800 | F3: 2100 | G3: 11370 | H3: Medium | I3: Col C may be a running total
A4: 3 | B4: =README!$C$4 -> 45949 | C4: Dh. Mill | D4: Dh. Milk | E4: 1860 | F4: 1450 | G4: 52125 | H4: Low | I4: Col C hard to read (52125?)
A5: 4 | B5: =README!$C$4 -> 45949 | C5: J. Mill | D5: J. Milk | E5: 860 | F5: 860 | H5: Low | I5: Col C reads like 7.50 - unclear, left blank
A6: 5 | B6: =README!$C$4 -> 45949 | C6: Jaila Mill | D6: Jaila Milk | E6: 3600 | F6: 4100 | H6: Medium
A7: 6 | B7: =README!$C$4 -> 45949 | C7: Pol. Mill | D7: Pol. Milk | H7: Medium | I7: Name written, no amount
A8: 7 | B8: =README!$C$4 -> 45949 | C8: Food | D8: Food | E8: 650 | F8: 650 | H8: Medium
A9: 8 | B9: =README!$C$4 -> 45949 | C9: Water | D9: Water | E9: 120 | F9: 120 | H9: Medium
A10: 9 | B10: =README!$C$4 -> 45949 | C10: Cutlet | D10: Cutlet | E10: 500 | F10: 500 | H10: Medium
A11: 10 | B11: =README!$C$4 -> 45949 | C11: Nuts | D11: Nuts | F11: 1935 | H11: Medium
A12: 11 | B12: =README!$C$4 -> 45949 | C12: Samsa | D12: Samsa | E12: 2100 | F12: 2100 | G12: 5200 | H12: Medium
A13: 12 | B13: =README!$C$4 -> 45949 | C13: G.J | D13: G.J (unclear) | F13: 2000 | H13: Low | I13: Item name unclear
A14: 13 | B14: =README!$C$4 -> 45949 | C14: C-gold | D14: C-gold (unclear) | E14: 5830 | F14: 6200 | G14: 4010 | H14: Low | I14: Largest line; item name unclear - please confirm
A15: 14 | B15: =README!$C$4 -> 45949 | C15: D-Snack | D15: D-Snack | E15: 2412 | F15: 2412 | H15: Medium | I15: Col C illegible
A16: 15 | B16: =README!$C$4 -> 45949 | C16: Bakery | D16: Bakery | F16: 357 | H16: Medium
A17: 16 | B17: =README!$C$4 -> 45949 | C17: Boli | D17: Boli | F17: 150 | G17: 100 | H17: Low | I17: Col C small note beside it
A18: 17 | B18: =README!$C$4 -> 45949 | C18: Sundal | D18: Sundal | E18: 400 | F18: 500 | H18: Medium
A19: 18 | B19: =README!$C$4 -> 45949 | C19: Chocke | D19: Chocolate? (unclear) | E19: 400 | F19: 400 | H19: Low
A20: 19 | B20: =README!$C$4 -> 45949 | C20: JOP | D20: JOP (unclear) | E20: 100 | F20: 100 | H20: Low | I20: Item name unclear
A21: 20 | B21: =README!$C$4 -> 45949 | C21: Coke Cola | D21: Coca-Cola | F21: 2707 | H21: Medium
A22: 21 | B22: =README!$C$4 -> 45949 | C22: Aquamar | D22: Aquamar (bottled water?) | E22: 1050 | F22: 1050 | H22: Medium
A23: 22 | B23: =README!$C$4 -> 45949 | C23: Soup | D23: Soup | E23: 40 | F23: 40 | H23: Medium
A24: 23 | B24: =README!$C$4 -> 45949 | C24: Paal Kova | D24: Paal Kova | E24: 400 | F24: 400 | H24: Medium
A25: 24 | B25: =README!$C$4 -> 45949 | C25: P.M.V | D25: P.M.V (unclear) | E25: 1800 | F25: 2000 | G25: 2200 | H25: Low | I25: Item name unclear
A26: 25 | B26: =README!$C$4 -> 45949 | C26: C-Yoll | D26: C-Yoll (unclear) | E26: 240 | F26: 240 | H26: Low | I26: Item name unclear
D27: Total (excl. R.F) | E27: =SUM(E3:E26) -> 24162 | F27: =SUM(F3:F26) -> 32371 | G27: =SUM(G3:G26) -> 75005
D28: Col C is a mixed column (totals/notes); its total is not meaningful.

Sheet Expenses
A1: Expense ID | B1: Date | C1: Branch ID | D1: Category | E1: Sub-category | F1: Amount (Rs) | G1: Payment mode | H1: Supplier / payee | I1: Description | J1: Entered by | K1: Approval status | L1: Source ledger line
A2: EXP-001 | B2: =README!$C$4 -> 45949 | C2: =README!$C$5 -> BR001 | D2: Milk | E2: Silk | F2: =Ledger_Raw!F3 -> 2100 | G2: Cash | I2: Silk Milk (ledger: Silk Mill) | K2: Pending | L2: =Ledger_Raw!A3 -> 2
A3: EXP-002 | B3: =README!$C$4 -> 45949 | C3: =README!$C$5 -> BR001 | D3: Milk | E3: Dh. | F3: =Ledger_Raw!F4 -> 1450 | G3: Cash | I3: Dh. Milk (ledger: Dh. Mill) | K3: Pending | L3: =Ledger_Raw!A4 -> 3
A4: EXP-003 | B4: =README!$C$4 -> 45949 | C4: =README!$C$5 -> BR001 | D4: Milk | E4: J. | F4: =Ledger_Raw!F5 -> 860 | G4: Cash | I4: J. Milk (ledger: J. Mill) | K4: Pending | L4: =Ledger_Raw!A5 -> 4
A5: EXP-004 | B5: =README!$C$4 -> 45949 | C5: =README!$C$5 -> BR001 | D5: Milk | E5: Jaila | F5: =Ledger_Raw!F6 -> 4100 | G5: Cash | I5: Jaila Milk (ledger: Jaila Mill) | K5: Pending | L5: =Ledger_Raw!A6 -> 5
A6: EXP-005 | B6: =README!$C$4 -> 45949 | C6: =README!$C$5 -> BR001 | D6: Snacks/raw materials | E6: Food | F6: =Ledger_Raw!F8 -> 650 | G6: Cash | I6: Food (ledger: Food) | K6: Pending | L6: =Ledger_Raw!A8 -> 7
A7: EXP-006 | B7: =README!$C$4 -> 45949 | C7: =README!$C$5 -> BR001 | D7: Miscellaneous | E7: Water | F7: =Ledger_Raw!F9 -> 120 | G7: Cash | I7: Water (ledger: Water) | K7: Pending | L7: =Ledger_Raw!A9 -> 8
A8: EXP-007 | B8: =README!$C$4 -> 45949 | C8: =README!$C$5 -> BR001 | D8: Snacks/raw materials | E8: Cutlet | F8: =Ledger_Raw!F10 -> 500 | G8: Cash | I8: Cutlet (ledger: Cutlet) | K8: Pending | L8: =Ledger_Raw!A10 -> 9
A9: EXP-008 | B9: =README!$C$4 -> 45949 | C9: =README!$C$5 -> BR001 | D9: Snacks/raw materials | E9: Nuts | F9: =Ledger_Raw!F11 -> 1935 | G9: Cash | I9: Nuts (ledger: Nuts) | K9: Pending | L9: =Ledger_Raw!A11 -> 10
A10: EXP-009 | B10: =README!$C$4 -> 45949 | C10: =README!$C$5 -> BR001 | D10: Snacks/raw materials | E10: Samsa | F10: =Ledger_Raw!F12 -> 2100 | G10: Cash | I10: Samsa (ledger: Samsa) | K10: Pending | L10: =Ledger_Raw!A12 -> 11
A11: EXP-010 | B11: =README!$C$4 -> 45949 | C11: =README!$C$5 -> BR001 | D11: Needs review | F11: =Ledger_Raw!F13 -> 2000 | G11: Cash | I11: G.J (unclear) (ledger: G.J) | K11: Pending | L11: =Ledger_Raw!A13 -> 12
A12: EXP-011 | B12: =README!$C$4 -> 45949 | C12: =README!$C$5 -> BR001 | D12: Needs review | F12: =Ledger_Raw!F14 -> 6200 | G12: Cash | I12: C-gold (unclear) (ledger: C-gold) | K12: Pending | L12: =Ledger_Raw!A14 -> 13
A13: EXP-012 | B13: =README!$C$4 -> 45949 | C13: =README!$C$5 -> BR001 | D13: Snacks/raw materials | E13: D-Snack | F13: =Ledger_Raw!F15 -> 2412 | G13: Cash | I13: D-Snack (ledger: D-Snack) | K13: Pending | L13: =Ledger_Raw!A15 -> 14
A14: EXP-013 | B14: =README!$C$4 -> 45949 | C14: =README!$C$5 -> BR001 | D14: Snacks/raw materials | E14: Bakery | F14: =Ledger_Raw!F16 -> 357 | G14: Cash | I14: Bakery (ledger: Bakery) | K14: Pending | L14: =Ledger_Raw!A16 -> 15
A15: EXP-014 | B15: =README!$C$4 -> 45949 | C15: =README!$C$5 -> BR001 | D15: Snacks/raw materials | E15: Boli | F15: =Ledger_Raw!F17 -> 150 | G15: Cash | I15: Boli (ledger: Boli) | K15: Pending | L15: =Ledger_Raw!A17 -> 16
A16: EXP-015 | B16: =README!$C$4 -> 45949 | C16: =README!$C$5 -> BR001 | D16: Snacks/raw materials | E16: Sundal | F16: =Ledger_Raw!F18 -> 500 | G16: Cash | I16: Sundal (ledger: Sundal) | K16: Pending | L16: =Ledger_Raw!A18 -> 17
A17: EXP-016 | B17: =README!$C$4 -> 45949 | C17: =README!$C$5 -> BR001 | D17: Snacks/raw materials | E17: Chocolate? | F17: =Ledger_Raw!F19 -> 400 | G17: Cash | I17: Chocolate? (unclear) (ledger: Chocke) | K17: Pending | L17: =Ledger_Raw!A19 -> 18
A18: EXP-017 | B18: =README!$C$4 -> 45949 | C18: =README!$C$5 -> BR001 | D18: Needs review | F18: =Ledger_Raw!F20 -> 100 | G18: Cash | I18: JOP (unclear) (ledger: JOP) | K18: Pending | L18: =Ledger_Raw!A20 -> 19
A19: EXP-018 | B19: =README!$C$4 -> 45949 | C19: =README!$C$5 -> BR001 | D19: Miscellaneous | E19: Cold drinks | F19: =Ledger_Raw!F21 -> 2707 | G19: Cash | I19: Coca-Cola (ledger: Coke Cola) | K19: Pending | L19: =Ledger_Raw!A21 -> 20
A20: EXP-019 | B20: =README!$C$4 -> 45949 | C20: =README!$C$5 -> BR001 | D20: Miscellaneous | E20: Water bottles | F20: =Ledger_Raw!F22 -> 1050 | G20: Cash | I20: Aquamar (bottled water?) (ledger: Aquamar) | K20: Pending | L20: =Ledger_Raw!A22 -> 21
A21: EXP-020 | B21: =README!$C$4 -> 45949 | C21: =README!$C$5 -> BR001 | D21: Snacks/raw materials | E21: Soup | F21: =Ledger_Raw!F23 -> 40 | G21: Cash | I21: Soup (ledger: Soup) | K21: Pending | L21: =Ledger_Raw!A23 -> 22
A22: EXP-021 | B22: =README!$C$4 -> 45949 | C22: =README!$C$5 -> BR001 | D22: Snacks/raw materials | E22: Paal Kova | F22: =Ledger_Raw!F24 -> 400 | G22: Cash | I22: Paal Kova (ledger: Paal Kova) | K22: Pending | L22: =Ledger_Raw!A24 -> 23
A23: EXP-022 | B23: =README!$C$4 -> 45949 | C23: =README!$C$5 -> BR001 | D23: Needs review | F23: =Ledger_Raw!F25 -> 2000 | G23: Cash | I23: P.M.V (unclear) (ledger: P.M.V) | K23: Pending | L23: =Ledger_Raw!A25 -> 24
A24: EXP-023 | B24: =README!$C$4 -> 45949 | C24: =README!$C$5 -> BR001 | D24: Needs review | F24: =Ledger_Raw!F26 -> 240 | G24: Cash | I24: C-Yoll (unclear) (ledger: C-Yoll) | K24: Pending | L24: =Ledger_Raw!A26 -> 25
E25: Total | F25: =SUM(F2:F24) -> 32371

Sheet Staff_Payments
A1: Record ID | B1: Date | C1: Branch ID | D1: Name | E1: Amount (Rs) | F1: Type (confirm) | G1: Status | H1: Notes
A2: SP-001 | B2: =README!$C$4 -> 45949 | C2: =README!$C$5 -> BR001 | D2: Shail | E2: =1000+300 -> 1300 | F2: Advance / salary (to confirm) | G2: Pending | H2: Written as 1000 + 300
A3: SP-002 | B3: =README!$C$4 -> 45949 | C3: =README!$C$5 -> BR001 | D3: Riyas | E3: 750 | F3: Advance / salary (to confirm) | G3: Pending
A4: SP-003 | B4: =README!$C$4 -> 45949 | C4: =README!$C$5 -> BR001 | D4: Amma | E4: 500 | F4: Advance / salary (to confirm) | G4: Pending | H4: Digit unclear (500 or 800)
A5: SP-004 | B5: =README!$C$4 -> 45949 | C5: =README!$C$5 -> BR001 | D5: Ahamed | E5: 1000 | F5: Advance / salary (to confirm) | G5: Pending
A6: SP-005 | B6: =README!$C$4 -> 45949 | C6: =README!$C$5 -> BR001 | D6: Ameen | E6: 650 | F6: Advance / salary (to confirm) | G6: Pending
A7: SP-006 | B7: =README!$C$4 -> 45949 | C7: =README!$C$5 -> BR001 | D7: Ajay | E7: 600 | F7: Advance / salary (to confirm) | G7: Pending
A8: SP-007 | B8: =README!$C$4 -> 45949 | C8: =README!$C$5 -> BR001 | D8: Hitham | F8: Advance / salary (to confirm) | G8: Pending | H8: Name written, no amount
A9: SP-008 | B9: =README!$C$4 -> 45949 | C9: =README!$C$5 -> BR001 | D9: Karman | E9: 1400 | F9: Advance / salary (to confirm) | G9: Pending
A10: SP-009 | B10: =README!$C$4 -> 45949 | C10: =README!$C$5 -> BR001 | D10: Lakshi | E10: 600 | F10: Advance / salary (to confirm) | G10: Pending
A11: SP-010 | B11: =README!$C$4 -> 45949 | C11: =README!$C$5 -> BR001 | D11: Dhanraj | E11: 650 | F11: Advance / salary (to confirm) | G11: Pending
A12: SP-011 | B12: =README!$C$4 -> 45949 | C12: =README!$C$5 -> BR001 | D12: Rajendra | E12: 650 | F12: Advance / salary (to confirm) | G12: Pending | H12: Could be 660
A13: SP-012 | B13: =README!$C$4 -> 45949 | C13: =README!$C$5 -> BR001 | D13: Beer | E13: 570 | F13: Advance / salary (to confirm) | G13: Pending | H13: May be a name or an item - please confirm
A14: SP-013 | B14: =README!$C$4 -> 45949 | C14: =README!$C$5 -> BR001 | D14: MD | E14: 200 | F14: Advance / salary (to confirm) | G14: Pending | H14: A circled 500 is written next to it - not added
A15: SP-014 | B15: =README!$C$4 -> 45949 | C15: =README!$C$5 -> BR001 | D15: Nabil | E15: 400 | F15: Advance / salary (to confirm) | G15: Pending
A16: SP-015 | B16: =README!$C$4 -> 45949 | C16: =README!$C$5 -> BR001 | D16: Aasif | E16: 500 | F16: Advance / salary (to confirm) | G16: Pending
D17: Total | E17: =SUM(E2:E16) -> 9770

Sheet Daily_Closing
A1: Daily Cash Reconciliation / Closing (SRS sections 5 and 6)
A3: Date | B3: =README!$C$4 -> 45949
A4: Branch ID | B4: =README!$C$5 -> BR001
A5: Opening cash | B5: =Ledger_Raw!F2 -> 2000
A6: Total sales (enter)
A7: Cash sales (enter)
A8: UPI sales (enter)
A9: Card / bank sales (enter)
A10: Credit sales (enter)
A11: Sales check: Total - (Cash+UPI+Card+Credit) | B11: =B6-SUM(B7:B10) -> 0
A12: Cash expenses / purchases | B12: =SUMIFS(Expenses!F2:F24,Expenses!G2:G24,"Cash") -> 32371
A13: Staff payments (assumed cash) | B13: =Staff_Payments!E17 -> 9770
A14: Expected closing cash | B14: =B5+B7-B12-B13 -> -40141
A15: Actual closing cash (enter)
A16: Cash surplus / (shortage) | B16: =IF(B15="","",B15-B14)
A17: Variance reason (required if not zero)
A18: Closing status | B18: Pending Closing
A20: Expected closing = Opening cash + Cash sales - Cash expenses/purchases - Staff payments. Sales and actual cash were not on the handwritten page.

Sheet Category_Summary
A1: Category | B1: Amount (Rs) | C1: % of total
A2: Milk | B2: =SUMIFS(Expenses!F2:F24,Expenses!D2:D24,A2) -> 8510 | C2: =IF($B$6=0,0,B2/$B$6) -> 0.26288962
A3: Snacks/raw materials | B3: =SUMIFS(Expenses!F2:F24,Expenses!D2:D24,A3) -> 9444 | C3: =IF($B$6=0,0,B3/$B$6) -> 0.29174261
A4: Miscellaneous | B4: =SUMIFS(Expenses!F2:F24,Expenses!D2:D24,A4) -> 3877 | C4: =IF($B$6=0,0,B4/$B$6) -> 0.11976769
A5: Needs review | B5: =SUMIFS(Expenses!F2:F24,Expenses!D2:D24,A5) -> 10540 | C5: =IF($B$6=0,0,B5/$B$6) -> 0.32560007
A6: Total | B6: =SUM(B2:B5) -> 32371
A8: Check vs Ledger_Raw Col B total | B8: =B6-Ledger_Raw!F27 -> 0 | C8: Should be 0 (opening cash row excluded)
